README.md
setup.py
pydatapack/__init__.py
pydatapack/utils.py
pydatapack.egg-info/PKG-INFO
pydatapack.egg-info/SOURCES.txt
pydatapack.egg-info/dependency_links.txt
pydatapack.egg-info/requires.txt
pydatapack.egg-info/top_level.txt
pydatapack/compiler/__init__.py
pydatapack/compiler/core.py
pydatapack/mc/__init__.py
pydatapack/mc/basic_commands.py
pydatapack/mc/gamemode.py
pydatapack/mc/special.py
pydatapack/mc/target.py
pydatapack/mc/internal/__init__.py
pydatapack/mc/internal/exceptions.py
pydatapack/mc/internal/general.py
pydatapack/mc/internal/parsers.py
pydatapack/mc/scoreboard/__init__.py
pydatapack/mc/scoreboard/scoreboard.py