Metadata-Version: 1.0
Name: pydatapack
Version: 0.1
Summary: pydatapack
